django_simple_third_party_jwt_dev_dashboard/__init__.py
django_simple_third_party_jwt_dev_dashboard/admin.py
django_simple_third_party_jwt_dev_dashboard/apps.py
django_simple_third_party_jwt_dev_dashboard/forms.py
django_simple_third_party_jwt_dev_dashboard/models.py
django_simple_third_party_jwt_dev_dashboard/settings.py
django_simple_third_party_jwt_dev_dashboard/tests.py
django_simple_third_party_jwt_dev_dashboard/urls.py
django_simple_third_party_jwt_dev_dashboard/views.py
django_simple_third_party_jwt_dev_dashboard/templates/base.html
django_simple_third_party_jwt_dev_dashboard/templates/dashboard.html
django_simple_third_party_jwt_dev_dashboard/templates/login.html
django_simple_third_party_jwt_dev_dashboard-0.2.3.dist-info/LICENSE
django_simple_third_party_jwt_dev_dashboard-0.2.3.dist-info/METADATA
django_simple_third_party_jwt_dev_dashboard-0.2.3.dist-info/WHEEL
django_simple_third_party_jwt_dev_dashboard-0.2.3.dist-info/top_level.txt
django_simple_third_party_jwt_dev_dashboard-0.2.3.dist-info/RECORD
