Metadata-Version: 2.1
Name: django-simple-third-party-jwt-dev-dashboard
Version: 0.2.3
Summary: Dashboard for using JWT with 3rd party login.
Home-page: https://github.com/NatLee/Django-Simple-3rd-Party-JWT-Dev-Dashboard
Author: Nat Lee
Author-email: natlee.work@gmail.com
Project-URL: Documentation, https://github.com/natlee/Django-Simple-3rd-Party-JWT-Dev-Dashboard
Project-URL: Bug Reports, https://github.com/natlee/Django-Simple-3rd-Party-JWT-Dev-Dashboard/issues
Project-URL: Source Code, https://github.com/natlee/Django-Simple-3rd-Party-JWT-Dev-Dashboard
Keywords: django,jwt,3rd party login,dashboard,toolbox
Classifier: Development Status :: 5 - Production/Stable
Classifier: Intended Audience :: Developers
Classifier: Topic :: Software Development :: Build Tools
Classifier: Programming Language :: Python :: 3
Classifier: Programming Language :: Python :: 3.8
Classifier: Programming Language :: Python :: 3.9
Classifier: Programming Language :: Python :: 3.10
Classifier: Programming Language :: Python :: 3.11
Classifier: Programming Language :: Python :: 3.12
Classifier: Programming Language :: Python :: 3 :: Only
Classifier: License :: OSI Approved :: MIT License
Classifier: Operating System :: OS Independent
Requires-Python: >=3.8
License-File: LICENSE
Requires-Dist: django>=4.0.0
Requires-Dist: djangorestframework
Requires-Dist: django-simple-third-party-jwt>=0.2.3
Requires-Dist: drf-yasg
Requires-Dist: django-bootstrap3
Provides-Extra: dev
Requires-Dist: check-manifest; extra == "dev"
